dynamic_psst_compiler.py
enhanced_psst_compiler.py
psst_compiler.py
psst_cost_tracker.py
psst_hybrid_integration.py
psst_openai.py
psst_ultimate.py
psst_toolkit-3.2.0.data/scripts/psst-hybrid
psst_toolkit-3.2.0.data/scripts/psst-learn
psst_toolkit-3.2.0.data/scripts/psst-openai
psst_toolkit-3.2.0.dist-info/METADATA
psst_toolkit-3.2.0.dist-info/WHEEL
psst_toolkit-3.2.0.dist-info/entry_points.txt
psst_toolkit-3.2.0.dist-info/top_level.txt
psst_toolkit-3.2.0.dist-info/RECORD
