Metadata-Version: 2.2
Name: psst-toolkit
Version: 3.2.0
Summary: Prompt Symbol Standard Technology - 88.6% token reduction with perfect semantic fidelity
Home-page: https://github.com/goldsteinmarcmd/psst
Author: Marc Goldstein
Author-email: Marc Goldstein <marcgoldstein@example.edu>
Maintainer-email: Marc Goldstein <marcgoldstein@example.edu>
License: MIT
Project-URL: Homepage, https://github.com/goldsteinmarcmd/psst
Project-URL: Documentation, https://github.com/goldsteinmarcmd/psst/blob/main/PSST_USER_MANUAL.md
Project-URL: Repository, https://github.com/goldsteinmarcmd/psst
Project-URL: Bug Tracker, https://github.com/goldsteinmarcmd/psst/issues
Keywords: ai,prompting,compression,tokens,openai,gpt,llm,efficiency,cost-optimization,session-management,cost-tracking,token-validation
Classifier: Development Status :: 5 - Production/Stable
Classifier: Intended Audience :: Developers
Classifier: Intended Audience :: Science/Research
Classifier: License :: OSI Approved :: MIT License
Classifier: Operating System :: OS Independent
Classifier: Programming Language :: Python :: 3
Classifier: Programming Language :: Python :: 3.7
Classifier: Programming Language :: Python :: 3.8
Classifier: Programming Language :: Python :: 3.9
Classifier: Programming Language :: Python :: 3.10
Classifier: Programming Language :: Python :: 3.11
Classifier: Topic :: Software Development :: Compilers
Classifier: Topic :: Text Processing :: Linguistic
Classifier: Topic :: Scientific/Engineering :: Artificial Intelligence
Classifier: Topic :: Software Development :: Libraries :: Python Modules
Requires-Python: >=3.7
Requires-Dist: requests>=2.25.0
Requires-Dist: jellyfish>=0.9.0
Requires-Dist: numpy>=1.19.0
Requires-Dist: pandas>=1.3.0
Provides-Extra: dev
Requires-Dist: pytest>=6.0; extra == "dev"
Requires-Dist: black>=21.0; extra == "dev"
Requires-Dist: flake8>=3.8; extra == "dev"
Provides-Extra: openai
Requires-Dist: openai>=1.0.0; extra == "openai"
Provides-Extra: enhanced
Requires-Dist: pandas>=1.3.0; extra == "enhanced"
Dynamic: author
Dynamic: home-page
Dynamic: requires-python
